README
setup.py
mixpanel_django/__init__.py
mixpanel_django/models.py
mixpanel_django/tests.py
mixpanel_django/views.py
mixpanel_django.egg-info/PKG-INFO
mixpanel_django.egg-info/SOURCES.txt
mixpanel_django.egg-info/dependency_links.txt
mixpanel_django.egg-info/requires.txt
mixpanel_django.egg-info/top_level.txt
mixpanel_django/backends/__init__.py
mixpanel_django/backends/beanstalk.py
mixpanel_django/backends/direct.py
mixpanel_django/backends/dummy.py
mixpanel_django/example/__init__.py
mixpanel_django/example/manage.py
mixpanel_django/example/settings.py
mixpanel_django/example/urls.py
mixpanel_django/example/mp_example/__init__.py
mixpanel_django/example/mp_example/models.py
mixpanel_django/example/mp_example/tests.py
mixpanel_django/example/mp_example/urls.py
mixpanel_django/example/mp_example/views.py
mixpanel_django/templatetags/__init__.py
mixpanel_django/templatetags/mp_tags.py