Metadata-Version: 1.0
Name: mixpanel-django
Version: 0.1
Summary: django reuseable app, it can simply track events use mixpanel API
Home-page: https://bitbucket.org/fla.sam/mixpanel_django/
Author: fla.sam
Author-email: fla.sam@gmail.com
License: Apache Licence 2.0
Keywords: python django mixpanel
Platform: UNKNOWN
